latex_python2025_task/__init__.py
latex_python2025_task/utils.py
latex_python2025_task-0.1.0.dist-info/METADATA
latex_python2025_task-0.1.0.dist-info/WHEEL
latex_python2025_task-0.1.0.dist-info/RECORD
