Metadata-Version: 2.1
Name: latex_python2025_task
Version: 0.1.0
Summary: 
Author: Evgenii
Author-email: eugenysvirin@gmail.com
Requires-Python: >=3.10,<4.0
Classifier: Programming Language :: Python :: 3
Classifier: Programming Language :: Python :: 3.10
Classifier: Programming Language :: Python :: 3.11
Classifier: Programming Language :: Python :: 3.12
Requires-Dist: latex (>=0.7.0,<0.8.0)
Requires-Dist: pdflatex (>=0.1.3,<0.2.0)
